{"title":"NBA 2014-10-29 Lakers vs Suns 720p 60fps","uid":11329351,"size":3586901355,"categoryP":"video","categoryS":"hd___tv_shows","magnet":"?xt=urn:btih:04a77cadeb8cbb579a59b1d1854d252689aaa7a2&amp;dn=NBA+2014-10-29+Lakers+vs+Suns+720p+60fps&amp;tr=udp%3A%2F%2Ftracker.openbittorrent.com%3A80&amp;tr=udp%3A%2F%2Fopen.demonii.com%3A1337&amp;tr=udp%3A%2F%2Ftracker.coppersurfer.tk%3A6969&amp;tr=udp%3A%2F%2Fexodus.desync.com%3A6969","seeders":1,"leechers":0,"uploader":"Road2HD","files":1,"time":1414659641,"description":"NBA 2014-10-29 Lakers vs Suns 720p 60fps\n\nLanguage : English\n\nCredit: eternityw\n\nVideo : 1280x720, 59.94 fps, 4400 kbps","torrent":{"xt":"urn:btih:04a77cadeb8cbb579a59b1d1854d252689aaa7a2","amp;dn":"NBA+2014-10-29+Lakers+vs+Suns+720p+60fps","amp;tr":["udp%3A%2F%2Ftracker.openbittorrent.com%3A80","udp%3A%2F%2Fopen.demonii.com%3A1337","udp%3A%2F%2Ftracker.coppersurfer.tk%3A6969","udp%3A%2F%2Fexodus.desync.com%3A6969"],"infoHash":"04a77cadeb8cbb579a59b1d1854d252689aaa7a2","infoHashBuffer":{"type":"Buffer","data":[4,167,124,173,235,140,187,87,154,89,177,209,133,77,37,38,137,170,167,162]},"announce":[],"urlList":[]}}