{"title":"The Healing of Sergei Rachmaninov - BBC Radio Drama","uid":8086350,"size":42401554,"categoryP":"audio","categoryS":"other","magnet":"?xt=urn:btih:1508a005a2ace48a63e7e0d3daba6e1c594edbc8&amp;dn=The+Healing+of+Sergei+Rachmaninov+-+BBC+Radio+Drama&amp;tr=udp%3A%2F%2Ftracker.openbittorrent.com%3A80&amp;tr=udp%3A%2F%2Fopen.demonii.com%3A1337&amp;tr=udp%3A%2F%2Ftracker.coppersurfer.tk%3A6969&amp;tr=udp%3A%2F%2Fexodus.desync.com%3A6969","seeders":1,"leechers":0,"uploader":"Pigman58","files":1,"time":1359630052,"description":"Biographical drama by Martyn Wade, telling the remarkable story behind the composition of Sergei Rachmaninov's celebrated Second Piano Concerto.","torrent":{"xt":"urn:btih:1508a005a2ace48a63e7e0d3daba6e1c594edbc8","amp;dn":"The+Healing+of+Sergei+Rachmaninov+-+BBC+Radio+Drama","amp;tr":["udp%3A%2F%2Ftracker.openbittorrent.com%3A80","udp%3A%2F%2Fopen.demonii.com%3A1337","udp%3A%2F%2Ftracker.coppersurfer.tk%3A6969","udp%3A%2F%2Fexodus.desync.com%3A6969"],"infoHash":"1508a005a2ace48a63e7e0d3daba6e1c594edbc8","infoHashBuffer":{"type":"Buffer","data":[21,8,160,5,162,172,228,138,99,231,224,211,218,186,110,28,89,78,219,200]},"announce":[],"urlList":[]}}