{"title":"PLURALSIGHT ANGULARJS UNIT TESTING IN DEPTH USING NGMOCK TUTORIA","uid":12797007,"size":512106314,"categoryP":"other","categoryS":"other","magnet":"?xt=urn:btih:1d7770a3e0e624a8eb425179d553a3f3d21c2cff&amp;dn=PLURALSIGHT+ANGULARJS+UNIT+TESTING+IN+DEPTH+USING+NGMOCK+TUTORIA&amp;tr=udp%3A%2F%2Ftracker.leechers-paradise.org%3A6969&amp;tr=udp%3A%2F%2Fzer0day.ch%3A1337&amp;tr=udp%3A%2F%2Fopen.demonii.com%3A1337&amp;tr=udp%3A%2F%2Ftracker.coppersurfer.tk%3A6969&amp;tr=udp%3A%2F%2Fexodus.desync.com%3A6969","seeders":1,"leechers":1,"uploader":"BarCraft","files":746,"time":1447985642,"description":"This course introduces the ngMock module for unit testing\r\nin AngularJS. The course will cover this module\r\nextensively, giving viewers a solid foundation for unit","torrent":{"xt":"urn:btih:1d7770a3e0e624a8eb425179d553a3f3d21c2cff","amp;dn":"PLURALSIGHT+ANGULARJS+UNIT+TESTING+IN+DEPTH+USING+NGMOCK+TUTORIA","amp;tr":["udp%3A%2F%2Ftracker.leechers-paradise.org%3A6969","udp%3A%2F%2Fzer0day.ch%3A1337","udp%3A%2F%2Fopen.demonii.com%3A1337","udp%3A%2F%2Ftracker.coppersurfer.tk%3A6969","udp%3A%2F%2Fexodus.desync.com%3A6969"],"infoHash":"1d7770a3e0e624a8eb425179d553a3f3d21c2cff","infoHashBuffer":{"type":"Buffer","data":[29,119,112,163,224,230,36,168,235,66,81,121,213,83,163,243,210,28,44,255]},"announce":[],"urlList":[]}}