{"title":"Amazonia.1985.DVDRip-Morsan(SweSub)","uid":4228166,"size":734877948,"categoryP":"video","categoryS":"movies","magnet":"?xt=urn:btih:21d84aa82c47b2217fc396b0cc055364c0ccbeeb&amp;dn=Amazonia.1985.DVDRip-Morsan%28SweSub%29&amp;tr=udp%3A%2F%2Ftracker.openbittorrent.com%3A80&amp;tr=udp%3A%2F%2Fopen.demonii.com%3A1337&amp;tr=udp%3A%2F%2Ftracker.coppersurfer.tk%3A6969&amp;tr=udp%3A%2F%2Fexodus.desync.com%3A6969","seeders":1,"leechers":0,"uploader":"truskan","files":4,"time":1212909226,"description":"           Amazonia: The Catherine Miles Story (1985) [Swe HardSub]\n\n\n\n\nMovie: Amazonia: The Catherine Miles Story (1985) &lt;a href=&quot;\nhttp://www.imdb.com/title/tt0091902/&quot; rel=&quot;nofollow&quot; target=&quot;_NEW&quot;&gt;\nhttp://www.imdb.com/title/tt0091902/&lt;/a&gt;\nUser Rating: 3.5/10 (387 votes)\nGenre: Adventure | Drama | Horror | Romance\nFiles: 1x700,13 MB\nVideo: XviD 1013 KB/s 608 x 336 @25fps\nAudio: MPEG-1 Layer 3 (MP3) 125 KB/s (VBR)\nSource: DVD PAL\nLanguage: English\nSubtitles: Swe (Hardsub)\n\nAlso Known As:\nSchiave bianche: violenza in Amazzonia \nCannibal Holocaust 2: The Catherine Miles Story (Europe: English title)\nCaptive Women VII: White Slave\nForest Slave (USA)\nWhite Slave \n\n\n\n\nPlot\nAn 18 year old Catherine Miles graduates from her boarding school \nand takes a trip with her parents to the Amazon. While on a boat \nride, her parents are brutally murdered by a local cannibal tribe \nand she is taken prisoner. In order to survive, she adopts the \ncustoms of the tribe with the help of a warrior who has fallen in \nlove with her, all the while planning vengeance for her parents&amp;#039; \ndeath. He later helps her to escape, and now free, she goes to \nfind who exactly was behind the death of her parents.\n\n\n\n\nAvi Info\nFile Name ..........: Amazonia.1985.DVDRip-Morsan.avi\nTotal Size (Bytes) .: 734 140 416 Bytes\nTotal Size (KB) ....: 716 934 KB\nTotal Size (MB) ....: 700,13 MB\nTotal Streams ......: 2 Stream(s)\nFile Size Correct ..: Yes\n\nVideo Size (Bytes) .: 652 944 125 Bytes\nVideo Size (KB) ....: 637 641 KB\nVideo Size (MB) ....: 622,70 MB\nVideo Length .......: 01:25:55\nVideo Codec Code ...: XVID\nVideo Codec Name ...: XviD MPEG-4 codec\nVideo Bitrate ......: 1013 KB/s\nResolution .........: 608 x 336\nAspect Ratio .......: 1.80:1\nTotal Frames .......: 128864 Frames\nFramerate ..........: 25 FPS\nColor Depth ........: 24 Bits\nQuality Factor .....: 0,198 B/px\nPacked Bitstream ...: No\n\nAudio Size (Bytes) .: 81 186 095 Bytes\nAudio Size (KB) ....: 79 283 KB\nAudio Size (MB) ....: 77,43 MB\nAudio Length .......: 01:25:55\nAudio Codec Code ...: 85 (0x0055)\nAudio Codec Name ...: MPEG-1 Layer 3 (MP3)\nAudio Bitrate ......: 125 KB/s (VBR)\nChannels ...........: 2 Ch\nSampling Rate ......: 48000 Hz\n","torrent":{"xt":"urn:btih:21d84aa82c47b2217fc396b0cc055364c0ccbeeb","amp;dn":"Amazonia.1985.DVDRip-Morsan%28SweSub%29","amp;tr":["udp%3A%2F%2Ftracker.openbittorrent.com%3A80","udp%3A%2F%2Fopen.demonii.com%3A1337","udp%3A%2F%2Ftracker.coppersurfer.tk%3A6969","udp%3A%2F%2Fexodus.desync.com%3A6969"],"infoHash":"21d84aa82c47b2217fc396b0cc055364c0ccbeeb","infoHashBuffer":{"type":"Buffer","data":[33,216,74,168,44,71,178,33,127,195,150,176,204,5,83,100,192,204,190,235]},"announce":[],"urlList":[]}}