{"title":"Citizen Kane [1941, BDRip] Rus-Eng HQ Underverse","uid":9067086,"size":2338981888,"categoryP":"video","categoryS":"movies","magnet":"?xt=urn:btih:29c797a772364b018d136ff88cc4d1b94c3fb695&amp;dn=Citizen+Kane+%5B1941%2C+BDRip%5D+Rus-Eng+HQ+Underverse&amp;tr=udp%3A%2F%2Ftracker.openbittorrent.com%3A80&amp;tr=udp%3A%2F%2Fopen.demonii.com%3A1337&amp;tr=udp%3A%2F%2Ftracker.coppersurfer.tk%3A6969&amp;tr=udp%3A%2F%2Fexodus.desync.com%3A6969","seeders":1,"leechers":0,"uploader":"lonelyb0y","files":-1,"time":1382126161,"description":"Quality: BDRip\n\nDuration: 01:59:23\n\nVideo: XviD, 720x524, 1813 kbps\nAudio 1: Russian MVO [Somewax], AC3 2.0, 192 kbps\nAudio 2: Russian MVO [DVD Magic], AC3 2.0, 192 kbps\nAudio 3: Russian MVO [Film Prestige], AC3 2.0, 192 kbps\nAudio 4: English, AC3 2.0, 192 kbps\n\nVisit Underverse.su for more information","torrent":{"xt":"urn:btih:29c797a772364b018d136ff88cc4d1b94c3fb695","amp;dn":"Citizen+Kane+%5B1941%2C+BDRip%5D+Rus-Eng+HQ+Underverse","amp;tr":["udp%3A%2F%2Ftracker.openbittorrent.com%3A80","udp%3A%2F%2Fopen.demonii.com%3A1337","udp%3A%2F%2Ftracker.coppersurfer.tk%3A6969","udp%3A%2F%2Fexodus.desync.com%3A6969"],"infoHash":"29c797a772364b018d136ff88cc4d1b94c3fb695","infoHashBuffer":{"type":"Buffer","data":[41,199,151,167,114,54,75,1,141,19,111,248,140,196,209,185,76,63,182,149]},"announce":[],"urlList":[]}}