{"title":"Big Tits At School - Alison Tyler (The Study Buddy).mp4","uid":12339783,"size":427052143,"categoryP":"porn","categoryS":"movie_clips","magnet":"?xt=urn:btih:2aaf37d00f02aa12a8c0433706035dd10db143a1&amp;dn=Big+Tits+At+School+-+Alison+Tyler+%28The+Study+Buddy%29.mp4&amp;tr=udp%3A%2F%2Ftracker.openbittorrent.com%3A80&amp;tr=udp%3A%2F%2Fopen.demonii.com%3A1337&amp;tr=udp%3A%2F%2Ftracker.coppersurfer.tk%3A6969&amp;tr=udp%3A%2F%2Fexodus.desync.com%3A6969","seeders":1,"leechers":0,"uploader":"Piratepr0n","files":1,"time":1441289174,"description":"-------------------------------------------------------------------------------------\nName:\nBig Tits At School - Alison Tyler (The Study Buddy).mp4\n-------------------------------------------------------------------------------------\nFile list:\nBig Tits At School - Alison Tyler (The Study Buddy).mp4 (407 MiB | 854x480 | 47min 47s | MPEG-4) &lt;a href=&quot;\nhttp://imgfapper.com/img-55e83883f07f0.html&quot; rel=&quot;nofollow&quot; target=&quot;_NEW&quot;&gt;\nhttp://imgfapper.com/img-55e83883f07f0.html&lt;/a&gt;","torrent":{"xt":"urn:btih:2aaf37d00f02aa12a8c0433706035dd10db143a1","amp;dn":"Big+Tits+At+School+-+Alison+Tyler+%28The+Study+Buddy%29.mp4","amp;tr":["udp%3A%2F%2Ftracker.openbittorrent.com%3A80","udp%3A%2F%2Fopen.demonii.com%3A1337","udp%3A%2F%2Ftracker.coppersurfer.tk%3A6969","udp%3A%2F%2Fexodus.desync.com%3A6969"],"infoHash":"2aaf37d00f02aa12a8c0433706035dd10db143a1","infoHashBuffer":{"type":"Buffer","data":[42,175,55,208,15,2,170,18,168,192,67,55,6,3,93,209,13,177,67,161]},"announce":[],"urlList":[]}}