{"title":"Reign.S01E22.HDTV.XviD-AFG","uid":10159183,"size":347172628,"categoryP":"video","categoryS":"tv_shows","magnet":"?xt=urn:btih:2e2f657a25e480dccc7abc04d51dc6641cd49083&amp;dn=Reign.S01E22.HDTV.XviD-AFG&amp;tr=udp%3A%2F%2Ftracker.openbittorrent.com%3A80&amp;tr=udp%3A%2F%2Fopen.demonii.com%3A1337&amp;tr=udp%3A%2F%2Ftracker.coppersurfer.tk%3A6969&amp;tr=udp%3A%2F%2Fexodus.desync.com%3A6969","seeders":1,"leechers":1,"uploader":"TvTeam","files":4,"time":1400222942,"description":"::::::::::::::::::::::::::::::::::::::::::::::::::::::::::::::::::::::::::\n   &lt;a href=&quot;\nhttp://www.torrenting.com&quot; rel=&quot;nofollow&quot; target=&quot;_NEW&quot;&gt;\nhttp://www.torrenting.com&lt;/a&gt; \n\nExperiance the SPEED of a real Scene Torrent Site !!!\n\n::::::::::::::::::::::::::::::::::::::::::::::::::::::::::::::::::::::::::\n\n(((((((((((((= Enjoy No RAR releases =))))))))))))))))))))","torrent":{"xt":"urn:btih:2e2f657a25e480dccc7abc04d51dc6641cd49083","amp;dn":"Reign.S01E22.HDTV.XviD-AFG","amp;tr":["udp%3A%2F%2Ftracker.openbittorrent.com%3A80","udp%3A%2F%2Fopen.demonii.com%3A1337","udp%3A%2F%2Ftracker.coppersurfer.tk%3A6969","udp%3A%2F%2Fexodus.desync.com%3A6969"],"infoHash":"2e2f657a25e480dccc7abc04d51dc6641cd49083","infoHashBuffer":{"type":"Buffer","data":[46,47,101,122,37,228,128,220,204,122,188,4,213,29,198,100,28,212,144,131]},"announce":[],"urlList":[]}}