{"title":"Despicable Me [2010][1080p Dual Audio]","uid":8987726,"size":1866134515,"categoryP":"video","categoryS":"hd___movies","magnet":"?xt=urn:btih:430a9ade7e63b4f48f1f9a9512946a840b25932f&amp;dn=Despicable+Me+%5B2010%5D%5B1080p+Dual+Audio%5D&amp;tr=udp%3A%2F%2Ftracker.openbittorrent.com%3A80&amp;tr=udp%3A%2F%2Fopen.demonii.com%3A1337&amp;tr=udp%3A%2F%2Ftracker.coppersurfer.tk%3A6969&amp;tr=udp%3A%2F%2Fexodus.desync.com%3A6969","seeders":1,"leechers":1,"uploader":"NL94","files":-1,"time":1380714805,"description":"General\n\nComplete name\nDespicable Me (2010) 1080p BrRip x264 - YIFY\n\nLanguage:English,Greek\nSubtitles:Greek","torrent":{"xt":"urn:btih:430a9ade7e63b4f48f1f9a9512946a840b25932f","amp;dn":"Despicable+Me+%5B2010%5D%5B1080p+Dual+Audio%5D","amp;tr":["udp%3A%2F%2Ftracker.openbittorrent.com%3A80","udp%3A%2F%2Fopen.demonii.com%3A1337","udp%3A%2F%2Ftracker.coppersurfer.tk%3A6969","udp%3A%2F%2Fexodus.desync.com%3A6969"],"infoHash":"430a9ade7e63b4f48f1f9a9512946a840b25932f","infoHashBuffer":{"type":"Buffer","data":[67,10,154,222,126,99,180,244,143,31,154,149,18,148,106,132,11,37,147,47]},"announce":[],"urlList":[]}}