{"title":"Bojhena Se Bojhena (2012) Title Song - HD - MKV - {K!llERoY512}.","uid":8710477,"size":102740774,"categoryP":"video","categoryS":"music_videos","magnet":"?xt=urn:btih:643d3a0ec279e849e9f672b9f73841a08e54841a&amp;dn=Bojhena+Se+Bojhena+%282012%29+Title+Song+-+HD+-+MKV+-+%7BK%21llERoY512%7D.&amp;tr=udp%3A%2F%2Ftracker.openbittorrent.com%3A80&amp;tr=udp%3A%2F%2Fopen.demonii.com%3A1337&amp;tr=udp%3A%2F%2Ftracker.coppersurfer.tk%3A6969&amp;tr=udp%3A%2F%2Fexodus.desync.com%3A6969","seeders":1,"leechers":0,"uploader":"KilleR512","files":1,"time":1374225482,"description":"[img]http://yuq.me/users/21/716/wBAnhFzLd3.png[/img]\n\n\nBojhena Se Bojhena (2012) Title Song - HD - MKV - {K!llERoY512}\n\n-:: MOVIE INFO ::-\nMovie name : Bojhena Se Bojhena\nYear : 2012\nGenres : Drama | Romance\nProducer : Shree Venkatesh Films\nDirector : Raj Chakraborty\nCast : Soham Chakraborty, Payel Sarkar, Abir Chattopadhyay, Mimi Chakraborty, etc.\nSinger : Arijit Singh\nMusic Director : Arindam, Indradeep Dasgupta\t \nLanguage : Bengali\nFile Size : 98 MB\nRespects To : K!llERoY512[/b][/quote]\n\n-:: GENERAL INFO ::-\nName : Bojhena Se Bojhena (2012) Title Song - HD - MKV - {K!llERoY512}.mkv\nFormat : Matroska\nFile size : 98 MiB\nDuration : 3mn 58s\nVideo Format : AVC (Advanced Video Codec)\nBit rate : 3000 Kbps\nWidth : 1280 pixels\nHeight : 544 pixels\nDisplay aspect ratio : 2.35:1\nAudio Format : AC-3 (Audio Coding 3)\nBit rate : 448 Kbps\nChannel(s) : 2 channels\nSampling rate : 44.1 KHz\n\n-:: SCREENSHOT ::-\n &lt;a href=&quot; http://s20.postimg.org/vexryuo4d/Bojhena_Se_Bojhena_2012_Title_Song_HD_MKV.jpg&quot; rel=&quot;nofollow&quot; target=&quot;_NEW&quot;&gt; http://s20.postimg.org/vexryuo4d/Bojhena_Se_Bojhena_2012_Title_Song_HD_MKV.jpg&lt;/a&gt;\n\n","torrent":{"xt":"urn:btih:643d3a0ec279e849e9f672b9f73841a08e54841a","amp;dn":"Bojhena+Se+Bojhena+%282012%29+Title+Song+-+HD+-+MKV+-+%7BK%21llERoY512%7D.","amp;tr":["udp%3A%2F%2Ftracker.openbittorrent.com%3A80","udp%3A%2F%2Fopen.demonii.com%3A1337","udp%3A%2F%2Ftracker.coppersurfer.tk%3A6969","udp%3A%2F%2Fexodus.desync.com%3A6969"],"infoHash":"643d3a0ec279e849e9f672b9f73841a08e54841a","infoHashBuffer":{"type":"Buffer","data":[100,61,58,14,194,121,232,73,233,246,114,185,247,56,65,160,142,84,132,26]},"announce":[],"urlList":[]}}