{"title":"Eddie.Stobart.Trucks.and.Trailers.S05E04.HDTV.XviD-AFG","uid":8508487,"size":378873885,"categoryP":"video","categoryS":"tv_shows","magnet":"?xt=urn:btih:7ecf5ae20bb89958d2f7876a14759c8e23bbcb2c&amp;dn=Eddie.Stobart.Trucks.and.Trailers.S05E04.HDTV.XviD-AFG&amp;tr=udp%3A%2F%2Ftracker.openbittorrent.com%3A80&amp;tr=udp%3A%2F%2Fopen.demonii.com%3A1337&amp;tr=udp%3A%2F%2Ftracker.coppersurfer.tk%3A6969&amp;tr=udp%3A%2F%2Fexodus.desync.com%3A6969","seeders":1,"leechers":0,"uploader":"TvTeam","files":4,"time":1369499359,"description":"::::::::::::::::::::::::::::::::::::::::::::::::::::::::::::::::::::::::::\n  &lt;a href=&quot;\nhttp://www.torrenting.com&quot; rel=&quot;nofollow&quot; target=&quot;_NEW&quot;&gt;\nhttp://www.torrenting.com&lt;/a&gt;\n\n::::::::::::::::::::::::::::::::::::::::::::::::::::::::::::::::::::::::::\n\n(((((((((((((= Enjoy No RAR releases =))))))))))))))))))))\n\n\nMust Try:  &lt;a href=&quot; http://www.torrenting.com&quot; rel=&quot;nofollow&quot; target=&quot;_NEW&quot;&gt; http://www.torrenting.com&lt;/a&gt;","torrent":{"xt":"urn:btih:7ecf5ae20bb89958d2f7876a14759c8e23bbcb2c","amp;dn":"Eddie.Stobart.Trucks.and.Trailers.S05E04.HDTV.XviD-AFG","amp;tr":["udp%3A%2F%2Ftracker.openbittorrent.com%3A80","udp%3A%2F%2Fopen.demonii.com%3A1337","udp%3A%2F%2Ftracker.coppersurfer.tk%3A6969","udp%3A%2F%2Fexodus.desync.com%3A6969"],"infoHash":"7ecf5ae20bb89958d2f7876a14759c8e23bbcb2c","infoHashBuffer":{"type":"Buffer","data":[126,207,90,226,11,184,153,88,210,247,135,106,20,117,156,142,35,187,203,44]},"announce":[],"urlList":[]}}