{"title":"IvanaFukalot - Stuffing My Peach - Ivana [720p].mp4","uid":9670214,"size":350650005,"categoryP":"porn","categoryS":"movie_clips","magnet":"?xt=urn:btih:8af85d06614a2757043c367525d0529d1869923a&amp;dn=IvanaFukalot+-+Stuffing+My+Peach+-+Ivana+%5B720p%5D.mp4&amp;tr=udp%3A%2F%2Ftracker.openbittorrent.com%3A80&amp;tr=udp%3A%2F%2Fopen.demonii.com%3A1337&amp;tr=udp%3A%2F%2Ftracker.coppersurfer.tk%3A6969&amp;tr=udp%3A%2F%2Fexodus.desync.com%3A6969","seeders":1,"leechers":0,"uploader":"C3Porno","files":-1,"time":1393443298,"description":"IvanaFukalot - Stuffing My Peach - Ivana [720p].mp4\n\n2014, Teen, Masturbation, Solo, Outdoor, HD, XXX, Adult\n\n1280 x 720\n\n00:12:35\n\n334.41 MB\n\nScreens\n &lt;a href=&quot;\nhttp://www.euro-pic.eu/share-B0A4_530E3226.html&quot; rel=&quot;nofollow&quot; target=&quot;_NEW&quot;&gt;\nhttp://www.euro-pic.eu/share-B0A4_530E3226.html&lt;/a&gt;\n &lt;a href=&quot;\nhttp://www.euro-pic.eu/share-9D23_530E3226.html&quot; rel=&quot;nofollow&quot; target=&quot;_NEW&quot;&gt;\nhttp://www.euro-pic.eu/share-9D23_530E3226.html&lt;/a&gt;\n &lt;a href=&quot;\nhttp://www.euro-pic.eu/share-0DEC_530E3226.html&quot; rel=&quot;nofollow&quot; target=&quot;_NEW&quot;&gt;\nhttp://www.euro-pic.eu/share-0DEC_530E3226.html&lt;/a&gt;","torrent":{"xt":"urn:btih:8af85d06614a2757043c367525d0529d1869923a","amp;dn":"IvanaFukalot+-+Stuffing+My+Peach+-+Ivana+%5B720p%5D.mp4","amp;tr":["udp%3A%2F%2Ftracker.openbittorrent.com%3A80","udp%3A%2F%2Fopen.demonii.com%3A1337","udp%3A%2F%2Ftracker.coppersurfer.tk%3A6969","udp%3A%2F%2Fexodus.desync.com%3A6969"],"infoHash":"8af85d06614a2757043c367525d0529d1869923a","infoHashBuffer":{"type":"Buffer","data":[138,248,93,6,97,74,39,87,4,60,54,117,37,208,82,157,24,105,146,58]},"announce":[],"urlList":[]}}