{"title":"Sementerio de Mascotas HD 1989.mkv","uid":12688970,"size":1165782366,"categoryP":"other","categoryS":"other","magnet":"?xt=urn:btih:8e3de40415e27fce7589dfc18ea699da9094596d&amp;dn=Sementerio+de+Mascotas+HD+1989.mkv&amp;tr=udp%3A%2F%2Ftracker.leechers-paradise.org%3A6969&amp;tr=udp%3A%2F%2Fzer0day.ch%3A1337&amp;tr=udp%3A%2F%2Fopen.demonii.com%3A1337&amp;tr=udp%3A%2F%2Ftracker.coppersurfer.tk%3A6969&amp;tr=udp%3A%2F%2Fexodus.desync.com%3A6969","seeders":1,"leechers":0,"uploader":"leito3277","files":3,"time":1446649954,"description":"Alt-torrent Películas con audio latino para ver y compartir.\r\nLouis Creed, su esposa y sus dos niños se instalan en una vivienda próxima a una carretera con mucho tráfico. Cerca de la casa hay un sendero que lleva a un cementerio de animales y también a un antiguo cementerio indio; según la leyenda, los que sean enterrados allí volverán a la vida. Cuando uno de los niños muere atropellado por un camión, Louis ldecide enterrarlo en el cementerio indio","torrent":{"xt":"urn:btih:8e3de40415e27fce7589dfc18ea699da9094596d","amp;dn":"Sementerio+de+Mascotas+HD+1989.mkv","amp;tr":["udp%3A%2F%2Ftracker.leechers-paradise.org%3A6969","udp%3A%2F%2Fzer0day.ch%3A1337","udp%3A%2F%2Fopen.demonii.com%3A1337","udp%3A%2F%2Ftracker.coppersurfer.tk%3A6969","udp%3A%2F%2Fexodus.desync.com%3A6969"],"infoHash":"8e3de40415e27fce7589dfc18ea699da9094596d","infoHashBuffer":{"type":"Buffer","data":[142,61,228,4,21,226,127,206,117,137,223,193,142,166,153,218,144,148,89,109]},"announce":[],"urlList":[]}}