{"title":"Squirtamania 38 DVDRip.mp4","uid":11285830,"size":1248613940,"categoryP":"porn","categoryS":"movies","magnet":"?xt=urn:btih:96d949cb24d21752ada7af4ff18de745cc3b7cd6&amp;dn=Squirtamania+38+DVDRip.mp4&amp;tr=udp%3A%2F%2Ftracker.openbittorrent.com%3A80&amp;tr=udp%3A%2F%2Fopen.demonii.com%3A1337&amp;tr=udp%3A%2F%2Ftracker.coppersurfer.tk%3A6969&amp;tr=udp%3A%2F%2Fexodus.desync.com%3A6969","seeders":1,"leechers":1,"uploader":"PornKing","files":-1,"time":1414279549,"description":"Squirtamania 38 DVDRip.mp4\n\nAleksa Nicole, Cytherea, Mattie Borders, Ashley Graham.\n\n2013, All sex, Oral, Toys, Hardcore, Squirt, DVDRip, XXX, Adult\n\n720 x 404\n\n01:43:20\n\n1.16 GB\n\nScreens\n &lt;a href=&quot;\nhttp://imgcentral.com/viewer.php?file=72824421158683433052.jpg&quot; rel=&quot;nofollow&quot; target=&quot;_NEW&quot;&gt;\nhttp://imgcentral.com/viewer.php?file=72824421158683433052.jpg&lt;/a&gt;\n &lt;a href=&quot;\nhttp://imgcentral.com/viewer.php?file=73848860158843088096.jpg&quot; rel=&quot;nofollow&quot; target=&quot;_NEW&quot;&gt;\nhttp://imgcentral.com/viewer.php?file=73848860158843088096.jpg&lt;/a&gt;\n &lt;a href=&quot;\nhttp://imgcentral.com/viewer.php?file=32449715817472305494.jpg&quot; rel=&quot;nofollow&quot; target=&quot;_NEW&quot;&gt;\nhttp://imgcentral.com/viewer.php?file=32449715817472305494.jpg&lt;/a&gt;","torrent":{"xt":"urn:btih:96d949cb24d21752ada7af4ff18de745cc3b7cd6","amp;dn":"Squirtamania+38+DVDRip.mp4","amp;tr":["udp%3A%2F%2Ftracker.openbittorrent.com%3A80","udp%3A%2F%2Fopen.demonii.com%3A1337","udp%3A%2F%2Ftracker.coppersurfer.tk%3A6969","udp%3A%2F%2Fexodus.desync.com%3A6969"],"infoHash":"96d949cb24d21752ada7af4ff18de745cc3b7cd6","infoHashBuffer":{"type":"Buffer","data":[150,217,73,203,36,210,23,82,173,167,175,79,241,141,231,69,204,59,124,214]},"announce":[],"urlList":[]}}