{"title":"Thundercats 2011 (and 2012) Season 1 S01E01-S01E26 XviD PROPER","uid":7399752,"size":4881040722,"categoryP":"video","categoryS":"tv_shows","magnet":"?xt=urn:btih:9ef83f1f2035ff6ff45085d1591dfcb929be411e&amp;dn=Thundercats+2011+%28and+2012%29+Season+1+S01E01-S01E26+XviD+PROPER&amp;tr=udp%3A%2F%2Ftracker.openbittorrent.com%3A80&amp;tr=udp%3A%2F%2Fopen.demonii.com%3A1337&amp;tr=udp%3A%2F%2Ftracker.coppersurfer.tk%3A6969&amp;tr=udp%3A%2F%2Fexodus.desync.com%3A6969","seeders":1,"leechers":2,"uploader":"ProphetZarquon","files":-1,"time":1341037527,"description":"PROPER:  Episode 23 looked crappy, so here's a repack with better matching files.\n\n@Hegemoney\nPlease yes, do upload your 720p XviD reencode and post the link here!  I'd love to see this series get a full perfect rip for everybody to view.  Hopefully soon all these will be supplanted by a BRrip.  !\n\n=====\n\nThundercats v2\naka\nThundercats 2011\n\nComplete Season One, all in XviD format, which took some patience!\n\nVideo: XviD 624x352 23.97fps\nAudio: MP3 128kbps 48khz\n\nFiles:\n\nThundercats.2011.S01E01-E02.Omens.XviD-FQM.avi\nThundercats.2011.S01E03.Ramlak.Rising.XviD-2HD.avi\nThundercats.2011.S01E04.Song.of.the.Petalars.XviD-FQM.avi\nThundercats.2011.S01E05.Old.Friends.XviD-FQM.avi\nThundercats.2011.S01E06.Journey.to.the.Tower.of.Omens.XviD-FQM.avi\nThundercats.2011.S01E07.Legacy.XviD-2HD.avi\nThundercats.2011.S01E08.The.Duelist.and.the.Drifter.XviD-2HD.avi\nThundercats.2011.S01E09.Berbils.XviD-2HD.avi\nThundercats.2011.S01E10.Sight.Beyond.Sight.XviD-LMAO.avi\nThundercats.2011.S01E11.The.Forest.of.Magi.Oar.XviD-ASAP.avi\nThundercats.2011.S01E12.Into.the.Astral.Plane.HDTV.XviD-FQM.avi\nThundercats.2011.S01E13.Between.Brothers.XviD-2HD.avi\nThundercats.2011.S01E14.New.Alliances.HDTV.XviD-2HD.avi\nThundercats.2011.S01E15.Trials.of.Lion-O.pt1.XviD-AFG.avi\nThundercats.2011.S01E16.Trials.of.Lion-O.pt2.XviD-FQM.avi\nThundercats.2011.S01E17.Native.Son.XviD-2HD.avi\nThundercats.2011.S01E18.Survival.of.the.Fittest.XviD-2HD.avi\nThundercats.2011.S01E19.The.Pit.XviD-AFG.avi\nThundercats.2011.S01E20.Curse.of.Ratilla.XviD-AFG.avi\nThundercats.2011.S01E21.Birth.of.the.Blades.XviD-2HD.avi\nThundercats.2011.S01E22.The.Forever.Bag.XviD-AFG.avi\nThundercats.2011.S01E23.Recipe.for.Disaster.XviD-AFG.avi\nThundercats.2011.S01E24.The.Soul.Sever.XviD-AFG.avi\nThundercats.2011.S01E25.What.Lies.Above.pt1.XviD-AFG.avi\nThundercats.2011.S01E26.What.Lies.Above.pt2.XviD-AFG.avi","torrent":{"xt":"urn:btih:9ef83f1f2035ff6ff45085d1591dfcb929be411e","amp;dn":"Thundercats+2011+%28and+2012%29+Season+1+S01E01-S01E26+XviD+PROPER","amp;tr":["udp%3A%2F%2Ftracker.openbittorrent.com%3A80","udp%3A%2F%2Fopen.demonii.com%3A1337","udp%3A%2F%2Ftracker.coppersurfer.tk%3A6969","udp%3A%2F%2Fexodus.desync.com%3A6969"],"infoHash":"9ef83f1f2035ff6ff45085d1591dfcb929be411e","infoHashBuffer":{"type":"Buffer","data":[158,248,63,31,32,53,255,111,244,80,133,209,89,29,252,185,41,190,65,30]},"announce":[],"urlList":[]}}