{"title":"Black Male Pale Tail 1","uid":11811914,"size":1466619904,"categoryP":"porn","categoryS":"movies","magnet":"?xt=urn:btih:c9130e045b660287afb404087858d1953d07a8ca&amp;dn=Black+Male+Pale+Tail+1&amp;tr=udp%3A%2F%2Ftracker.openbittorrent.com%3A80&amp;tr=udp%3A%2F%2Fopen.demonii.com%3A1337&amp;tr=udp%3A%2F%2Ftracker.coppersurfer.tk%3A6969&amp;tr=udp%3A%2F%2Fexodus.desync.com%3A6969","seeders":1,"leechers":0,"uploader":"digital_ripper","files":2,"time":1428856032,"description":"screens\n &lt;a href=&quot;\nhttp://www.mypornimage.com/adultimage/nir&quot; rel=&quot;nofollow&quot; target=&quot;_NEW&quot;&gt;\nhttp://www.mypornimage.com/adultimage/nir&lt;/a&gt; &lt;a href=&quot;\nhttp://www.mypornimage.com/adultimage/niw&quot; rel=&quot;nofollow&quot; target=&quot;_NEW&quot;&gt;\nhttp://www.mypornimage.com/adultimage/niw&lt;/a&gt; &lt;a href=&quot;\nhttp://www.mypornimage.com/adultimage/niY&quot; rel=&quot;nofollow&quot; target=&quot;_NEW&quot;&gt;\nhttp://www.mypornimage.com/adultimage/niY&lt;/a&gt;\n\n\n~~~~~~~~~~~~~~~~~~~~~~~~~~~~~~~~~~~~~~~~~~~~~~~~~~~~~~~~~~~~~~~~~~~~~~~~~~~~~~~\n\n                       ````````````````````````````````\n      Downloads your favourite porn movies only from digital_ripper accounts\n~~~~~~~~~~~~~~~~~~~~~~~~~~~~~~~~~~~~~~~~~~~~~~~~~~~~~~~~~~~~~~~~~~~~~~~~~~~~~~~","torrent":{"xt":"urn:btih:c9130e045b660287afb404087858d1953d07a8ca","amp;dn":"Black+Male+Pale+Tail+1","amp;tr":["udp%3A%2F%2Ftracker.openbittorrent.com%3A80","udp%3A%2F%2Fopen.demonii.com%3A1337","udp%3A%2F%2Ftracker.coppersurfer.tk%3A6969","udp%3A%2F%2Fexodus.desync.com%3A6969"],"infoHash":"c9130e045b660287afb404087858d1953d07a8ca","infoHashBuffer":{"type":"Buffer","data":[201,19,14,4,91,102,2,135,175,180,4,8,120,88,209,149,61,7,168,202]},"announce":[],"urlList":[]}}