{"title":"18OnlyGirls - A Big Deal - Agnese [1080p].wmv","uid":7267142,"size":817674887,"categoryP":"porn","categoryS":"hd___movies","magnet":"?xt=urn:btih:d89aa59738328889b8ea06541ff83a70441ee802&amp;dn=18OnlyGirls+-+A+Big+Deal+-+Agnese+%5B1080p%5D.wmv&amp;tr=udp%3A%2F%2Ftracker.openbittorrent.com%3A80&amp;tr=udp%3A%2F%2Fopen.demonii.com%3A1337&amp;tr=udp%3A%2F%2Ftracker.coppersurfer.tk%3A6969&amp;tr=udp%3A%2F%2Fexodus.desync.com%3A6969","seeders":1,"leechers":0,"uploader":"C3Porno","files":-1,"time":1336934881,"description":"18OnlyGirls - A Big Deal - Agnese [1080p].wmv\n\n2012, Teen, Masturbation, Toy Play, HD, XXX, Adult\n\n1920 x 1080\n\n00:15:08\n\n779.80 MB\n\nScreens\n &lt;a href=&quot;\nhttp://www.euro-pic.eu/share-F2EB_4FAFE67E.html&quot; rel=&quot;nofollow&quot; target=&quot;_NEW&quot;&gt;\nhttp://www.euro-pic.eu/share-F2EB_4FAFE67E.html&lt;/a&gt;\n &lt;a href=&quot;\nhttp://www.euro-pic.eu/share-5FE9_4FAFE67E.html&quot; rel=&quot;nofollow&quot; target=&quot;_NEW&quot;&gt;\nhttp://www.euro-pic.eu/share-5FE9_4FAFE67E.html&lt;/a&gt;\n &lt;a href=&quot;\nhttp://www.euro-pic.eu/share-C7A2_4FAFE67E.html&quot; rel=&quot;nofollow&quot; target=&quot;_NEW&quot;&gt;\nhttp://www.euro-pic.eu/share-C7A2_4FAFE67E.html&lt;/a&gt;\n &lt;a href=&quot;\nhttp://www.euro-pic.eu/share-DAF3_4FAFE67E.html&quot; rel=&quot;nofollow&quot; target=&quot;_NEW&quot;&gt;\nhttp://www.euro-pic.eu/share-DAF3_4FAFE67E.html&lt;/a&gt;","torrent":{"xt":"urn:btih:d89aa59738328889b8ea06541ff83a70441ee802","amp;dn":"18OnlyGirls+-+A+Big+Deal+-+Agnese+%5B1080p%5D.wmv","amp;tr":["udp%3A%2F%2Ftracker.openbittorrent.com%3A80","udp%3A%2F%2Fopen.demonii.com%3A1337","udp%3A%2F%2Ftracker.coppersurfer.tk%3A6969","udp%3A%2F%2Fexodus.desync.com%3A6969"],"infoHash":"d89aa59738328889b8ea06541ff83a70441ee802","infoHashBuffer":{"type":"Buffer","data":[216,154,165,151,56,50,136,137,184,234,6,84,31,248,58,112,68,30,232,2]},"announce":[],"urlList":[]}}