{"title":"Almost Human 2013 HDRip XviD-RARBG","uid":9777231,"size":673605666,"categoryP":"video","categoryS":"movies","magnet":"?xt=urn:btih:e530d65e5b3b9903f812c2d20d53be1431a0dbd5&amp;dn=Almost+Human+2013+HDRip+XviD-RARBG&amp;tr=udp%3A%2F%2Ftracker.openbittorrent.com%3A80&amp;tr=udp%3A%2F%2Fopen.demonii.com%3A1337&amp;tr=udp%3A%2F%2Ftracker.coppersurfer.tk%3A6969&amp;tr=udp%3A%2F%2Fexodus.desync.com%3A6969","seeders":1,"leechers":0,"uploader":"Drarbg","files":2,"time":1395051045,"description":"Almost Human 2013 HDRip XviD-RARBG\n-----------------------------------------\nScreens : &lt;a href=&quot;\nhttp://i.imgur.com/OGOk7mW.png&quot; rel=&quot;nofollow&quot; target=&quot;_NEW&quot;&gt;\nhttp://i.imgur.com/OGOk7mW.png&lt;/a&gt; &lt;a href=&quot;\nhttp://i.imgur.com/l50oMq7.png&quot; rel=&quot;nofollow&quot; target=&quot;_NEW&quot;&gt;\nhttp://i.imgur.com/l50oMq7.png&lt;/a&gt; &lt;a href=&quot;\nhttp://i.imgur.com/1mRiSxm.png&quot; rel=&quot;nofollow&quot; target=&quot;_NEW&quot;&gt;\nhttp://i.imgur.com/1mRiSxm.png&lt;/a&gt; &lt;a href=&quot;\nhttp://i.imgur.com/4vaI2cX.png&quot; rel=&quot;nofollow&quot; target=&quot;_NEW&quot;&gt;\nhttp://i.imgur.com/4vaI2cX.png&lt;/a&gt; &lt;a href=&quot;\nhttp://i.imgur.com/kn54n3T.png&quot; rel=&quot;nofollow&quot; target=&quot;_NEW&quot;&gt;\nhttp://i.imgur.com/kn54n3T.png&lt;/a&gt; &lt;a href=&quot;\nhttp://i.imgur.com/UKoXARz.png&quot; rel=&quot;nofollow&quot; target=&quot;_NEW&quot;&gt;\nhttp://i.imgur.com/UKoXARz.png&lt;/a&gt;\n\n","torrent":{"xt":"urn:btih:e530d65e5b3b9903f812c2d20d53be1431a0dbd5","amp;dn":"Almost+Human+2013+HDRip+XviD-RARBG","amp;tr":["udp%3A%2F%2Ftracker.openbittorrent.com%3A80","udp%3A%2F%2Fopen.demonii.com%3A1337","udp%3A%2F%2Ftracker.coppersurfer.tk%3A6969","udp%3A%2F%2Fexodus.desync.com%3A6969"],"infoHash":"e530d65e5b3b9903f812c2d20d53be1431a0dbd5","infoHashBuffer":{"type":"Buffer","data":[229,48,214,94,91,59,153,3,248,18,194,210,13,83,190,20,49,160,219,213]},"announce":[],"urlList":[]}}