{"title":"Regular.Show.S03E21.Big.Winner.720p.HDTV.x264-MiNDTHEGAP","uid":10257221,"size":260286996,"categoryP":"video","categoryS":"hd___tv_shows","magnet":"?xt=urn:btih:e959bce0646b6c36a6410267a3314b15e7cf9035&amp;dn=Regular.Show.S03E21.Big.Winner.720p.HDTV.x264-MiNDTHEGAP&amp;tr=udp%3A%2F%2Ftracker.openbittorrent.com%3A80&amp;tr=udp%3A%2F%2Fopen.demonii.com%3A1337&amp;tr=udp%3A%2F%2Ftracker.coppersurfer.tk%3A6969&amp;tr=udp%3A%2F%2Fexodus.desync.com%3A6969","seeders":1,"leechers":0,"uploader":"sceneline","files":10,"time":1401417217,"description":"-\n\nFor the sake of sharing, Please seed as long as you can\n\nEnjoy HD releases \n\n ............ NFO .............\n-\t\nFor more info about this show check NFO file\n-","torrent":{"xt":"urn:btih:e959bce0646b6c36a6410267a3314b15e7cf9035","amp;dn":"Regular.Show.S03E21.Big.Winner.720p.HDTV.x264-MiNDTHEGAP","amp;tr":["udp%3A%2F%2Ftracker.openbittorrent.com%3A80","udp%3A%2F%2Fopen.demonii.com%3A1337","udp%3A%2F%2Ftracker.coppersurfer.tk%3A6969","udp%3A%2F%2Fexodus.desync.com%3A6969"],"infoHash":"e959bce0646b6c36a6410267a3314b15e7cf9035","infoHashBuffer":{"type":"Buffer","data":[233,89,188,224,100,107,108,54,166,65,2,103,163,49,75,21,231,207,144,53]},"announce":[],"urlList":[]}}