{"title":"FemJoy.14.07.13.Olyana.T.What.Do.You.Want.Me.To.Do.XXX.IMAGESET-","uid":10551118,"size":50870034,"categoryP":"porn","categoryS":"other","magnet":"?xt=urn:btih:ec5f43745a4050e8b5b202a263463fe2e1107149&amp;dn=FemJoy.14.07.13.Olyana.T.What.Do.You.Want.Me.To.Do.XXX.IMAGESET-&amp;tr=udp%3A%2F%2Ftracker.openbittorrent.com%3A80&amp;tr=udp%3A%2F%2Fopen.demonii.com%3A1337&amp;tr=udp%3A%2F%2Ftracker.coppersurfer.tk%3A6969&amp;tr=udp%3A%2F%2Fexodus.desync.com%3A6969","seeders":1,"leechers":0,"uploader":"Drarbg","files":115,"time":1405297149,"description":" &lt;a href=&quot;https://rarbg.com&quot; rel=&quot;nofollow&quot; target=&quot;_NEW&quot;&gt;https://rarbg.com&lt;/a&gt;\n\nFemJoy.com_14.07.13.Olyana.T.What.Do.You.Want.Me.To.Do.XXX.IMAGESET-FuGLi\n","torrent":{"xt":"urn:btih:ec5f43745a4050e8b5b202a263463fe2e1107149","amp;dn":"FemJoy.14.07.13.Olyana.T.What.Do.You.Want.Me.To.Do.XXX.IMAGESET-","amp;tr":["udp%3A%2F%2Ftracker.openbittorrent.com%3A80","udp%3A%2F%2Fopen.demonii.com%3A1337","udp%3A%2F%2Ftracker.coppersurfer.tk%3A6969","udp%3A%2F%2Fexodus.desync.com%3A6969"],"infoHash":"ec5f43745a4050e8b5b202a263463fe2e1107149","infoHashBuffer":{"type":"Buffer","data":[236,95,67,116,90,64,80,232,181,178,2,162,99,70,63,226,225,16,113,73]},"announce":[],"urlList":[]}}