{"title":"Ice.Road.Truckers.S06E01.HDTV.x264-DUKES","uid":7327562,"size":451620866,"categoryP":"video","categoryS":"tv_shows","magnet":"?xt=urn:btih:f130fda35d7b84c079e471ee3e3ea8480c057a26&amp;dn=Ice.Road.Truckers.S06E01.HDTV.x264-DUKES&amp;tr=udp%3A%2F%2Ftracker.openbittorrent.com%3A80&amp;tr=udp%3A%2F%2Fopen.demonii.com%3A1337&amp;tr=udp%3A%2F%2Ftracker.coppersurfer.tk%3A6969&amp;tr=udp%3A%2F%2Fexodus.desync.com%3A6969","seeders":1,"leechers":0,"uploader":"chkm8te","files":1,"time":1338809656,"description":"Ice.Road.Truckers.S06E01.HDTV.x264-DUKES\n\nRelease Date: 2012 04 06\nRelease Size: 430 MiB\nSource: HDTV\nResolution: 720 x 406\nFramerate: 29.970 fps","torrent":{"xt":"urn:btih:f130fda35d7b84c079e471ee3e3ea8480c057a26","amp;dn":"Ice.Road.Truckers.S06E01.HDTV.x264-DUKES","amp;tr":["udp%3A%2F%2Ftracker.openbittorrent.com%3A80","udp%3A%2F%2Fopen.demonii.com%3A1337","udp%3A%2F%2Ftracker.coppersurfer.tk%3A6969","udp%3A%2F%2Fexodus.desync.com%3A6969"],"infoHash":"f130fda35d7b84c079e471ee3e3ea8480c057a26","infoHashBuffer":{"type":"Buffer","data":[241,48,253,163,93,123,132,192,121,228,113,238,62,62,168,72,12,5,122,38]},"announce":[],"urlList":[]}}