{"title":"Lynda- Access 2010: Queries in Depth","uid":12703559,"size":504217937,"categoryP":"other","categoryS":"other","magnet":"?xt=urn:btih:f45c41462ebde9abbb98427d5eacbc3e6cc6b1de&amp;dn=Lynda-+Access+2010%3A+Queries+in+Depth&amp;tr=udp%3A%2F%2Ftracker.leechers-paradise.org%3A6969&amp;tr=udp%3A%2F%2Fzer0day.ch%3A1337&amp;tr=udp%3A%2F%2Fopen.demonii.com%3A1337&amp;tr=udp%3A%2F%2Ftracker.coppersurfer.tk%3A6969&amp;tr=udp%3A%2F%2Fexodus.desync.com%3A6969","seeders":1,"leechers":1,"uploader":"3ljust","files":48,"time":1446802031,"description":"Access 2010: Queries in Depth\r\n3h 2m Intermediate Jun 16, 2011\r\n\r\n\r\n\r\nIn this course, author Adam Wilbert illustrates how to create and leverage real-world queries and turn raw data into usable information. The course covers setting up queries, performing calculations, using the built-in Access functions to further refine query results, and identifying top performers or areas for improvement based on a range of criteria.\r\nTopics include:\r\n\r\n    Naming conventions and best practices\r\n    Working with joins\r\n    Using comparison operators\r\n    Defining criteria for select queries\r\n    Creating parameter queries\r\n    Creating calculated fields\r\n    Working with dates and times\r\n    Using the Expression Builder\r\n    Creating conditional statements\r\n    Making, deleting and appending records\r\n    Building reports","torrent":{"xt":"urn:btih:f45c41462ebde9abbb98427d5eacbc3e6cc6b1de","amp;dn":"Lynda-+Access+2010%3A+Queries+in+Depth","amp;tr":["udp%3A%2F%2Ftracker.leechers-paradise.org%3A6969","udp%3A%2F%2Fzer0day.ch%3A1337","udp%3A%2F%2Fopen.demonii.com%3A1337","udp%3A%2F%2Ftracker.coppersurfer.tk%3A6969","udp%3A%2F%2Fexodus.desync.com%3A6969"],"infoHash":"f45c41462ebde9abbb98427d5eacbc3e6cc6b1de","infoHashBuffer":{"type":"Buffer","data":[244,92,65,70,46,189,233,171,187,152,66,125,94,172,188,62,108,198,177,222]},"announce":[],"urlList":[]}}