{"title":"Fresh And Easy 3 XXX DVDRip x264-Pr0nStarS","uid":7941710,"size":1755805618,"categoryP":"porn","categoryS":"movies","magnet":"?xt=urn:btih:f587de156e63b44d34779dc3b9923ffeccb74d36&amp;dn=Fresh+And+Easy+3+XXX+DVDRip+x264-Pr0nStarS&amp;tr=udp%3A%2F%2Ftracker.openbittorrent.com%3A80&amp;tr=udp%3A%2F%2Fopen.demonii.com%3A1337&amp;tr=udp%3A%2F%2Ftracker.coppersurfer.tk%3A6969&amp;tr=udp%3A%2F%2Fexodus.desync.com%3A6969","seeders":1,"leechers":2,"uploader":"xxxlavalxxx","files":2,"time":1355962730,"description":"Category All Sex, Legal Teen, Amateur \n  \nDirector Quasarman \n\nStarring Britney Young, Courtney Taylor, Rachel Rose, Mark Wood, Billy Glide, Tommy Pistol, Callie Carter \n\n\nBritney Young leads this cast of newbies who love to fuck! They're farm fresh and ready to show you everything they've got - and that's a lot! Tight little pussies and firm tender tits, these beauties can't wait to suck you deep down and spread their legs wide for a good old fashioned pounding! Throw these lovelies in your shopping cart today - they're Fresh &amp; Easy and up for anything! \n\n &lt;a href=&quot;\nhttp://tippic.eu/?v=puuu.jpg&quot; rel=&quot;nofollow&quot; target=&quot;_NEW&quot;&gt;\nhttp://tippic.eu/?v=puuu.jpg&lt;/a&gt;\n &lt;a href=&quot;\nhttp://tippic.eu/?v=psfande3mp.jpg&quot; rel=&quot;nofollow&quot; target=&quot;_NEW&quot;&gt;\nhttp://tippic.eu/?v=psfande3mp.jpg&lt;/a&gt;","torrent":{"xt":"urn:btih:f587de156e63b44d34779dc3b9923ffeccb74d36","amp;dn":"Fresh+And+Easy+3+XXX+DVDRip+x264-Pr0nStarS","amp;tr":["udp%3A%2F%2Ftracker.openbittorrent.com%3A80","udp%3A%2F%2Fopen.demonii.com%3A1337","udp%3A%2F%2Ftracker.coppersurfer.tk%3A6969","udp%3A%2F%2Fexodus.desync.com%3A6969"],"infoHash":"f587de156e63b44d34779dc3b9923ffeccb74d36","infoHashBuffer":{"type":"Buffer","data":[245,135,222,21,110,99,180,77,52,119,157,195,185,146,63,254,204,183,77,54]},"announce":[],"urlList":[]}}