{"title":"Star Wars Episode III - Revenge of the Sith[EN.PTBR.ES].iso","uid":7966789,"size":4687771648,"categoryP":"video","categoryS":"movies_dvdr","magnet":"?xt=urn:btih:f89d741954b3dcf652cf221acf2aa49ac12911c3&amp;dn=Star+Wars+Episode+III+-+Revenge+of+the+Sith%5BEN.PTBR.ES%5D.iso&amp;tr=udp%3A%2F%2Ftracker.openbittorrent.com%3A80&amp;tr=udp%3A%2F%2Fopen.demonii.com%3A1337&amp;tr=udp%3A%2F%2Ftracker.coppersurfer.tk%3A6969&amp;tr=udp%3A%2F%2Fexodus.desync.com%3A6969","seeders":1,"leechers":0,"uploader":"La_votanovo","files":1,"time":1356704762,"description":"Star Wars Episodio 3 Imagem DVD\n\nApos Baixarem deixem no seed pra semear galera","torrent":{"xt":"urn:btih:f89d741954b3dcf652cf221acf2aa49ac12911c3","amp;dn":"Star+Wars+Episode+III+-+Revenge+of+the+Sith%5BEN.PTBR.ES%5D.iso","amp;tr":["udp%3A%2F%2Ftracker.openbittorrent.com%3A80","udp%3A%2F%2Fopen.demonii.com%3A1337","udp%3A%2F%2Ftracker.coppersurfer.tk%3A6969","udp%3A%2F%2Fexodus.desync.com%3A6969"],"infoHash":"f89d741954b3dcf652cf221acf2aa49ac12911c3","infoHashBuffer":{"type":"Buffer","data":[248,157,116,25,84,179,220,246,82,207,34,26,207,42,164,154,193,41,17,195]},"announce":[],"urlList":[]}}