{"title":"Lost Bets - Bundle 20","uid":8907337,"size":1593689726,"categoryP":"porn","categoryS":"movie_clips","magnet":"?xt=urn:btih:f8b55ff9252dffa7bc60da1e0114e240bb27434f&amp;dn=Lost+Bets+-+Bundle+20&amp;tr=udp%3A%2F%2Ftracker.openbittorrent.com%3A80&amp;tr=udp%3A%2F%2Fopen.demonii.com%3A1337&amp;tr=udp%3A%2F%2Ftracker.coppersurfer.tk%3A6969&amp;tr=udp%3A%2F%2Fexodus.desync.com%3A6969","seeders":1,"leechers":1,"uploader":"zipomatic","files":4,"time":1378939598,"description":"Bundle 20!\n\nEpisode 056 - Lily, Elise, Amber and Sean - Pie Eating Contest (24:55)\nEpisode 059 - Lily Plays Strip Rock-Paper-Scissors (16:56)\nEpisode 091 - Heidi and Alexiel play Strip Rock-Paper-Scissors (05:14)\nEpisode 246 - Strip Poker with Ashley and Julie Vs You (32:03)\n\n\nScreens: (contains spoilers)\n  &lt;a href=&quot;\nhttp://www.stooorage.com/show/1811/9843457_lostbets-056-lily-elise-amber-sean-pieeating-contest-hd.jpeg&quot; rel=&quot;nofollow&quot; target=&quot;_NEW&quot;&gt;\nhttp://www.stooorage.com/show/1811/9843457_lostbets-056-lily-elise-amber-sean-pieeating-contest-hd.jpeg&lt;/a&gt; &lt;a href=&quot;\nhttp://www.stooorage.com/show/1811/9843458_lostbets-059-lily-plays-strip-rockpaperscissors-hd.jpeg&quot; rel=&quot;nofollow&quot; target=&quot;_NEW&quot;&gt;\nhttp://www.stooorage.com/show/1811/9843458_lostbets-059-lily-plays-strip-rockpaperscissors-hd.jpeg&lt;/a&gt; &lt;a href=&quot;\nhttp://www.stooorage.com/show/1811/9843459_lostbets-091-heidi-and-alexiel-play-strip-rock-paper-scissors.jpeg&quot; rel=&quot;nofollow&quot; target=&quot;_NEW&quot;&gt;\nhttp://www.stooorage.com/show/1811/9843459_lostbets-091-heidi-and-alexiel-play-strip-rock-paper-scissors.jpeg&lt;/a&gt; &lt;a href=&quot;\nhttp://www.stooorage.com/show/1811/9843460_lostbets-246-strip-poker-with-ashley-and-julie-vs-you-hd.jpeg&quot; rel=&quot;nofollow&quot; target=&quot;_NEW&quot;&gt;\nhttp://www.stooorage.com/show/1811/9843460_lostbets-246-strip-poker-with-ashley-and-julie-vs-you-hd.jpeg&lt;/a&gt;\n\n\n\n\n\n\n                            Check out my other uploads!\n \n                     &lt;a href=&quot; http://thepiratebay.se/user/zipomatic/&quot; rel=&quot;nofollow&quot; target=&quot;_NEW&quot;&gt; http://thepiratebay.se/user/zipomatic/&lt;/a&gt;\t","torrent":{"xt":"urn:btih:f8b55ff9252dffa7bc60da1e0114e240bb27434f","amp;dn":"Lost+Bets+-+Bundle+20","amp;tr":["udp%3A%2F%2Ftracker.openbittorrent.com%3A80","udp%3A%2F%2Fopen.demonii.com%3A1337","udp%3A%2F%2Ftracker.coppersurfer.tk%3A6969","udp%3A%2F%2Fexodus.desync.com%3A6969"],"infoHash":"f8b55ff9252dffa7bc60da1e0114e240bb27434f","infoHashBuffer":{"type":"Buffer","data":[248,181,95,249,37,45,255,167,188,96,218,30,1,20,226,64,187,39,67,79]},"announce":[],"urlList":[]}}